AUTHORS.rst
CONTRIBUTING.rst
MANIFEST.in
README.rst
VERSION
setup.cfg
setup.py
docs/Makefile
docs/authors.rst
docs/conf.py
docs/contributing.rst
docs/index.rst
docs/installation.rst
docs/marquee.rst
docs/modules.rst
docs/readme.rst
docs/usage.rst
marquee/__init__.py
marquee/formatter.py
marquee/handler.py
marquee.egg-info/PKG-INFO
marquee.egg-info/SOURCES.txt
marquee.egg-info/dependency_links.txt
marquee.egg-info/requires.txt
marquee.egg-info/top_level.txt