Metadata-Version: 1.0
Name: marquee
Version: 0.1.5
Summary: A simple Python logging formatter and handler for CloudWatch Events
Home-page: UNKNOWN
Author: Herkermer Sherwood
Author-email: theherk@gmail.com
License: UNKNOWN
Platform: all
